README.md
setup.py
rtimbo_version.egg-info/PKG-INFO
rtimbo_version.egg-info/SOURCES.txt
rtimbo_version.egg-info/dependency_links.txt
rtimbo_version.egg-info/top_level.txt
version/__init__.py
version/__main__.py
version/helpers.py
version/version.py