Metadata-Version: 2.1
Name: rtimbo-version
Version: 1.0.0
Summary: Version Comparator
Home-page: https://github.com/timbo-rafa/version
Author: Rafael
Author-email: timbo.rafa@gmail.com
License: UNKNOWN
Platform: UNKNOWN
Classifier: Programming Language :: Python :: 3
Classifier: License :: OSI Approved :: MIT License
Classifier: Operating System :: OS Independent
Requires-Python: >=3.6
